[
  {
    "__type__": "cc.SceneAsset",
    "_name": "RewardScene",
    "_objFlags": 0,
    "_native": "",
    "scene": {
      "__id__": 1
    }
  },
  {
    "__type__": "cc.Scene",
    "_name": "RewardScene",
    "_objFlags": 0,
    "_parent": null,
    "_children": [
      {
        "__id__": 2
      },
      {
        "__id__": 4
      },
      {
        "__id__": 7
      },
      {
        "__id__": 9
      }
    ],
    "_active": true,
    "_components": [],
    "_prefab": {
      "__id__": 48
    },
    "autoReleaseAssets": false,
    "_globals": {
      "__id__": 49
    },
    "_id": "162f724f-6712-42f0-af24-38bfc9672969"
  },
  {
    "__type__": "cc.Node",
    "_name": "ATRewardSceneScript",
    "_objFlags": 0,
    "_parent": {
      "__id__": 1
    },
    "_children": [],
    "_active": true,
    "_components": [
      {
        "__id__": 3
      }
    ],
    "_prefab": null,
    "_lpos": {
      "__type__": "cc.Vec3",
      "x": 0,
      "y": 0,
      "z": 0
    },
    "_lrot": {
      "__type__": "cc.Quat",
      "x": 0,
      "y": 0,
      "z": 0,
      "w": 1
    },
    "_lscale": {
      "__type__": "cc.Vec3",
      "x": 1,
      "y": 1,
      "z": 1
    },
    "_layer": 1073741824,
    "_euler": {
      "__type__": "cc.Vec3",
      "x": 0,
      "y": 0,
      "z": 0
    },
    "_id": "afGAUfzxZBBrmo4WInq11F"
  },
  {
    "__type__": "77f44wbrANOP4VV/pktIzil",
    "_name": "",
    "_objFlags": 0,
    "node": {
      "__id__": 2
    },
    "_enabled": true,
    "__prefab": null,
    "_id": "e3jClDrrNHDoAMvg3M94ex"
  },
  {
    "__type__": "cc.Node",
    "_name": "Main Light",
    "_objFlags": 0,
    "_parent": {
      "__id__": 1
    },
    "_children": [],
    "_active": true,
    "_components": [
      {
        "__id__": 5
      }
    ],
    "_prefab": null,
    "_lpos": {
      "__type__": "cc.Vec3",
      "x": 0,
      "y": 0,
      "z": 0
    },
    "_lrot": {
      "__type__": "cc.Quat",
      "x": -0.24999999999999997,
      "y": -0.24999999999999997,
      "z": -0.06698729810778066,
      "w": 0.9330127018922194
    },
    "_lscale": {
      "__type__": "cc.Vec3",
      "x": 1,
      "y": 1,
      "z": 1
    },
    "_layer": 1073741824,
    "_euler": {
      "__type__": "cc.Vec3",
      "x": -30,
      "y": -30,
      "z": 0
    },
    "_id": "c0y6F5f+pAvI805TdmxIjx"
  },
  {
    "__type__": "cc.DirectionalLight",
    "_name": "",
    "_objFlags": 0,
    "node": {
      "__id__": 4
    },
    "_enabled": true,
    "__prefab": null,
    "_color": {
      "__type__": "cc.Color",
      "r": 255,
      "g": 255,
      "b": 255,
      "a": 255
    },
    "_useColorTemperature": false,
    "_colorTemperature": 6550,
    "_staticSettings": {
      "__id__": 6
    },
    "_illuminanceHDR": 65000,
    "_illuminance": 65000,
    "_illuminanceLDR": 1.6927083333333335,
    "_id": "597uMYCbhEtJQc0ffJlcgA"
  },
  {
    "__type__": "cc.StaticLightSettings",
    "_baked": false,
    "_editorOnly": false,
    "_bakeable": false,
    "_castShadow": false
  },
  {
    "__type__": "cc.Node",
    "_name": "Main Camera",
    "_objFlags": 0,
    "_parent": {
      "__id__": 1
    },
    "_children": [],
    "_active": true,
    "_components": [
      {
        "__id__": 8
      }
    ],
    "_prefab": null,
    "_lpos": {
      "__type__": "cc.Vec3",
      "x": -606.147,
      "y": -170.023,
      "z": 632.939
    },
    "_lrot": {
      "__type__": "cc.Quat",
      "x": -0.27781593346944056,
      "y": -0.36497167621709875,
      "z": -0.11507512748638377,
      "w": 0.8811195706053617
    },
    "_lscale": {
      "__type__": "cc.Vec3",
      "x": 1,
      "y": 1,
      "z": 1
    },
    "_layer": 1073741824,
    "_euler": {
      "__type__": "cc.Vec3",
      "x": -35,
      "y": -45,
      "z": 0
    },
    "_id": "c9DMICJLFO5IeO07EPon7U"
  },
  {
    "__type__": "cc.Camera",
    "_name": "",
    "_objFlags": 0,
    "node": {
      "__id__": 7
    },
    "_enabled": true,
    "__prefab": null,
    "_projection": 0,
    "_priority": 0,
    "_fov": 0,
    "_fovAxis": 1,
    "_orthoHeight": 1917.41,
    "_near": 1,
    "_far": 1000,
    "_color": {
      "__type__": "cc.Color",
      "r": 51,
      "g": 51,
      "b": 51,
      "a": 255
    },
    "_depth": 1,
    "_stencil": 0,
    "_clearFlags": 7,
    "_rect": {
      "__type__": "cc.Rect",
      "x": 0,
      "y": 0,
      "width": 1,
      "height": 1
    },
    "_aperture": 19,
    "_shutter": 7,
    "_iso": 0,
    "_screenScale": 1,
    "_visibility": 1822425087,
    "_targetTexture": null,
    "_id": "7dWQTpwS5LrIHnc1zAPUtf"
  },
  {
    "__type__": "cc.Node",
    "_name": "Canvas",
    "_objFlags": 0,
    "_parent": {
      "__id__": 1
    },
    "_children": [
      {
        "__id__": 10
      },
      {
        "__id__": 12
      },
      {
        "__id__": 20
      },
      {
        "__id__": 28
      },
      {
        "__id__": 36
      }
    ],
    "_active": true,
    "_components": [
      {
        "__id__": 44
      },
      {
        "__id__": 45
      },
      {
        "__id__": 46
      },
      {
        "__id__": 47
      }
    ],
    "_prefab": null,
    "_lpos": {
      "__type__": "cc.Vec3",
      "x": 480,
      "y": 320,
      "z": 0
    },
    "_lrot": {
      "__type__": "cc.Quat",
      "x": 0,
      "y": 0,
      "z": 0,
      "w": 1
    },
    "_lscale": {
      "__type__": "cc.Vec3",
      "x": 1,
      "y": 1,
      "z": 1
    },
    "_layer": 33554432,
    "_euler": {
      "__type__": "cc.Vec3",
      "x": 0,
      "y": 0,
      "z": 0
    },
    "_id": "97+nS5WGJJZKVsej1NtglB"
  },
  {
    "__type__": "cc.Node",
    "_name": "Camera",
    "_objFlags": 0,
    "_parent": {
      "__id__": 9
    },
    "_children": [],
    "_active": true,
    "_components": [
      {
        "__id__": 11
      }
    ],
    "_prefab": null,
    "_lpos": {
      "__type__": "cc.Vec3",
      "x": 0,
      "y": 0,
      "z": 1000
    },
    "_lrot": {
      "__type__": "cc.Quat",
      "x": 0,
      "y": 0,
      "z": 0,
      "w": 1
    },
    "_lscale": {
      "__type__": "cc.Vec3",
      "x": 1,
      "y": 1,
      "z": 1
    },
    "_layer": 1073741824,
    "_euler": {
      "__type__": "cc.Vec3",
      "x": 0,
      "y": 0,
      "z": 0
    },
    "_id": "83eWbktpRMsaNO8w4i22kY"
  },
  {
    "__type__": "cc.Camera",
    "_name": "",
    "_objFlags": 0,
    "node": {
      "__id__": 10
    },
    "_enabled": true,
    "__prefab": null,
    "_projection": 0,
    "_priority": 1073741824,
    "_fov": 45,
    "_fovAxis": 0,
    "_orthoHeight": 320,
    "_near": 1,
    "_far": 2000,
    "_color": {
      "__type__": "cc.Color",
      "r": 0,
      "g": 0,
      "b": 0,
      "a": 255
    },
    "_depth": 1,
    "_stencil": 0,
    "_clearFlags": 6,
    "_rect": {
      "__type__": "cc.Rect",
      "x": 0,
      "y": 0,
      "width": 1,
      "height": 1
    },
    "_aperture": 19,
    "_shutter": 7,
    "_iso": 0,
    "_screenScale": 1,
    "_visibility": 41943040,
    "_targetTexture": null,
    "_id": "9aAZ/IdKRKnJ2LTOmujohI"
  },
  {
    "__type__": "cc.Node",
    "_name": "load ad",
    "_objFlags": 0,
    "_parent": {
      "__id__": 9
    },
    "_children": [
      {
        "__id__": 13
      }
    ],
    "_active": true,
    "_components": [
      {
        "__id__": 16
      },
      {
        "__id__": 17
      },
      {
        "__id__": 18
      }
    ],
    "_prefab": null,
    "_lpos": {
      "__type__": "cc.Vec3",
      "x": 0,
      "y": 100,
      "z": 0
    },
    "_lrot": {
      "__type__": "cc.Quat",
      "x": 0,
      "y": 0,
      "z": 0,
      "w": 1
    },
    "_lscale": {
      "__type__": "cc.Vec3",
      "x": 1,
      "y": 1,
      "z": 1
    },
    "_layer": 33554432,
    "_euler": {
      "__type__": "cc.Vec3",
      "x": 0,
      "y": 0,
      "z": 0
    },
    "_id": "d7SNwnLrND752CszlYKiqy"
  },
  {
    "__type__": "cc.Node",
    "_name": "load ad",
    "_objFlags": 512,
    "_parent": {
      "__id__": 12
    },
    "_children": [],
    "_active": true,
    "_components": [
      {
        "__id__": 14
      },
      {
        "__id__": 15
      }
    ],
    "_prefab": null,
    "_lpos": {
      "__type__": "cc.Vec3",
      "x": 0,
      "y": 0,
      "z": 0
    },
    "_lrot": {
      "__type__": "cc.Quat",
      "x": 0,
      "y": 0,
      "z": 0,
      "w": 1
    },
    "_lscale": {
      "__type__": "cc.Vec3",
      "x": 1,
      "y": 1,
      "z": 1
    },
    "_layer": 33554432,
    "_euler": {
      "__type__": "cc.Vec3",
      "x": 0,
      "y": 0,
      "z": 0
    },
    "_id": "facYRNMCdC6oxDo16OyxP4"
  },
  {
    "__type__": "cc.UITransform",
    "_name": "",
    "_objFlags": 0,
    "node": {
      "__id__": 13
    },
    "_enabled": true,
    "__prefab": null,
    "_contentSize": {
      "__type__": "cc.Size",
      "width": 200,
      "height": 80
    },
    "_anchorPoint": {
      "__type__": "cc.Vec2",
      "x": 0.5,
      "y": 0.5
    },
    "_id": "dekqk+hL5KlqEQDBrADfzd"
  },
  {
    "__type__": "cc.Label",
    "_name": "",
    "_objFlags": 0,
    "node": {
      "__id__": 13
    },
    "_enabled": true,
    "__prefab": null,
    "_visFlags": 0,
    "_customMaterial": null,
    "_srcBlendFactor": 2,
    "_dstBlendFactor": 4,
    "_color": {
      "__type__": "cc.Color",
      "r": 0,
      "g": 0,
      "b": 0,
      "a": 255
    },
    "_string": "LOAD AD",
    "_horizontalAlign": 1,
    "_verticalAlign": 1,
    "_actualFontSize": 20,
    "_fontSize": 20,
    "_fontFamily": "Arial",
    "_lineHeight": 40,
    "_overflow": 1,
    "_enableWrapText": false,
    "_font": null,
    "_isSystemFontUsed": true,
    "_spacingX": 0,
    "_isItalic": false,
    "_isBold": false,
    "_isUnderline": false,
    "_underlineHeight": 2,
    "_cacheMode": 0,
    "_id": "55EUL03g1Kbqk//Ei0LhDx"
  },
  {
    "__type__": "cc.UITransform",
    "_name": "",
    "_objFlags": 0,
    "node": {
      "__id__": 12
    },
    "_enabled": true,
    "__prefab": null,
    "_contentSize": {
      "__type__": "cc.Size",
      "width": 200,
      "height": 80
    },
    "_anchorPoint": {
      "__type__": "cc.Vec2",
      "x": 0.5,
      "y": 0.5
    },
    "_id": "98iWc2P4tPdrQgT9dWteS1"
  },
  {
    "__type__": "cc.Sprite",
    "_name": "",
    "_objFlags": 0,
    "node": {
      "__id__": 12
    },
    "_enabled": true,
    "__prefab": null,
    "_visFlags": 0,
    "_customMaterial": null,
    "_srcBlendFactor": 2,
    "_dstBlendFactor": 4,
    "_color": {
      "__type__": "cc.Color",
      "r": 255,
      "g": 255,
      "b": 255,
      "a": 255
    },
    "_spriteFrame": {
      "__uuid__": "20835ba4-6145-4fbc-a58a-051ce700aa3e@f9941",
      "__expectedType__": "cc.SpriteFrame"
    },
    "_type": 1,
    "_fillType": 0,
    "_sizeMode": 0,
    "_fillCenter": {
      "__type__": "cc.Vec2",
      "x": 0,
      "y": 0
    },
    "_fillStart": 0,
    "_fillRange": 0,
    "_isTrimmedMode": true,
    "_useGrayscale": false,
    "_atlas": null,
    "_id": "79CKIJ6N5GEaPOdiVcy2fV"
  },
  {
    "__type__": "cc.Button",
    "_name": "",
    "_objFlags": 0,
    "node": {
      "__id__": 12
    },
    "_enabled": true,
    "__prefab": null,
    "clickEvents": [
      {
        "__id__": 19
      }
    ],
    "_interactable": true,
    "_transition": 2,
    "_normalColor": {
      "__type__": "cc.Color",
      "r": 214,
      "g": 214,
      "b": 214,
      "a": 255
    },
    "_hoverColor": {
      "__type__": "cc.Color",
      "r": 211,
      "g": 211,
      "b": 211,
      "a": 255
    },
    "_pressedColor": {
      "__type__": "cc.Color",
      "r": 255,
      "g": 255,
      "b": 255,
      "a": 255
    },
    "_disabledColor": {
      "__type__": "cc.Color",
      "r": 124,
      "g": 124,
      "b": 124,
      "a": 255
    },
    "_normalSprite": {
      "__uuid__": "20835ba4-6145-4fbc-a58a-051ce700aa3e@f9941",
      "__expectedType__": "cc.SpriteFrame"
    },
    "_hoverSprite": {
      "__uuid__": "20835ba4-6145-4fbc-a58a-051ce700aa3e@f9941",
      "__expectedType__": "cc.SpriteFrame"
    },
    "_pressedSprite": {
      "__uuid__": "544e49d6-3f05-4fa8-9a9e-091f98fc2ce8@f9941",
      "__expectedType__": "cc.SpriteFrame"
    },
    "_disabledSprite": {
      "__uuid__": "951249e0-9f16-456d-8b85-a6ca954da16b@f9941",
      "__expectedType__": "cc.SpriteFrame"
    },
    "_duration": 0.1,
    "_zoomScale": 1.2,
    "_target": {
      "__id__": 12
    },
    "_id": "88zVF0IlBB0aIPL/evl6/P"
  },
  {
    "__type__": "cc.ClickEvent",
    "target": {
      "__id__": 2
    },
    "component": "",
    "_componentId": "77f44wbrANOP4VV/pktIzil",
    "handler": "loadAD",
    "customEventData": ""
  },
  {
    "__type__": "cc.Node",
    "_name": "is_ready",
    "_objFlags": 0,
    "_parent": {
      "__id__": 9
    },
    "_children": [
      {
        "__id__": 21
      }
    ],
    "_active": true,
    "_components": [
      {
        "__id__": 24
      },
      {
        "__id__": 25
      },
      {
        "__id__": 26
      }
    ],
    "_prefab": null,
    "_lpos": {
      "__type__": "cc.Vec3",
      "x": 0,
      "y": 1,
      "z": 0
    },
    "_lrot": {
      "__type__": "cc.Quat",
      "x": 0,
      "y": 0,
      "z": 0,
      "w": 1
    },
    "_lscale": {
      "__type__": "cc.Vec3",
      "x": 1,
      "y": 1,
      "z": 1
    },
    "_layer": 33554432,
    "_euler": {
      "__type__": "cc.Vec3",
      "x": 0,
      "y": 0,
      "z": 0
    },
    "_id": "e8u520/3dFCIUKlUBwm0Vs"
  },
  {
    "__type__": "cc.Node",
    "_name": "Is Ready",
    "_objFlags": 512,
    "_parent": {
      "__id__": 20
    },
    "_children": [],
    "_active": true,
    "_components": [
      {
        "__id__": 22
      },
      {
        "__id__": 23
      }
    ],
    "_prefab": null,
    "_lpos": {
      "__type__": "cc.Vec3",
      "x": 0,
      "y": 0,
      "z": 0
    },
    "_lrot": {
      "__type__": "cc.Quat",
      "x": 0,
      "y": 0,
      "z": 0,
      "w": 1
    },
    "_lscale": {
      "__type__": "cc.Vec3",
      "x": 1,
      "y": 1,
      "z": 1
    },
    "_layer": 33554432,
    "_euler": {
      "__type__": "cc.Vec3",
      "x": 0,
      "y": 0,
      "z": 0
    },
    "_id": "ccadg2DvxAi6v7lbQ1aqrD"
  },
  {
    "__type__": "cc.UITransform",
    "_name": "",
    "_objFlags": 0,
    "node": {
      "__id__": 21
    },
    "_enabled": true,
    "__prefab": null,
    "_contentSize": {
      "__type__": "cc.Size",
      "width": 100,
      "height": 40
    },
    "_anchorPoint": {
      "__type__": "cc.Vec2",
      "x": 0.5,
      "y": 0.5
    },
    "_id": "05tTsRaL1BkIScdVUN27v4"
  },
  {
    "__type__": "cc.Label",
    "_name": "",
    "_objFlags": 0,
    "node": {
      "__id__": 21
    },
    "_enabled": true,
    "__prefab": null,
    "_visFlags": 0,
    "_customMaterial": null,
    "_srcBlendFactor": 2,
    "_dstBlendFactor": 4,
    "_color": {
      "__type__": "cc.Color",
      "r": 0,
      "g": 0,
      "b": 0,
      "a": 255
    },
    "_string": "IS READY",
    "_horizontalAlign": 1,
    "_verticalAlign": 1,
    "_actualFontSize": 20,
    "_fontSize": 20,
    "_fontFamily": "Arial",
    "_lineHeight": 40,
    "_overflow": 1,
    "_enableWrapText": false,
    "_font": null,
    "_isSystemFontUsed": true,
    "_spacingX": 0,
    "_isItalic": false,
    "_isBold": false,
    "_isUnderline": false,
    "_underlineHeight": 2,
    "_cacheMode": 0,
    "_id": "12B47rdQ9L0r4h2SRjN0T+"
  },
  {
    "__type__": "cc.UITransform",
    "_name": "",
    "_objFlags": 0,
    "node": {
      "__id__": 20
    },
    "_enabled": true,
    "__prefab": null,
    "_contentSize": {
      "__type__": "cc.Size",
      "width": 200,
      "height": 80
    },
    "_anchorPoint": {
      "__type__": "cc.Vec2",
      "x": 0.5,
      "y": 0.5
    },
    "_id": "9evx7DEKpI25JvQHEwMQ8I"
  },
  {
    "__type__": "cc.Sprite",
    "_name": "",
    "_objFlags": 0,
    "node": {
      "__id__": 20
    },
    "_enabled": true,
    "__prefab": null,
    "_visFlags": 0,
    "_customMaterial": null,
    "_srcBlendFactor": 2,
    "_dstBlendFactor": 4,
    "_color": {
      "__type__": "cc.Color",
      "r": 255,
      "g": 255,
      "b": 255,
      "a": 255
    },
    "_spriteFrame": {
      "__uuid__": "20835ba4-6145-4fbc-a58a-051ce700aa3e@f9941",
      "__expectedType__": "cc.SpriteFrame"
    },
    "_type": 1,
    "_fillType": 0,
    "_sizeMode": 0,
    "_fillCenter": {
      "__type__": "cc.Vec2",
      "x": 0,
      "y": 0
    },
    "_fillStart": 0,
    "_fillRange": 0,
    "_isTrimmedMode": true,
    "_useGrayscale": false,
    "_atlas": null,
    "_id": "e4b+u+0QpPIaL+BLvTI6In"
  },
  {
    "__type__": "cc.Button",
    "_name": "",
    "_objFlags": 0,
    "node": {
      "__id__": 20
    },
    "_enabled": true,
    "__prefab": null,
    "clickEvents": [
      {
        "__id__": 27
      }
    ],
    "_interactable": true,
    "_transition": 2,
    "_normalColor": {
      "__type__": "cc.Color",
      "r": 214,
      "g": 214,
      "b": 214,
      "a": 255
    },
    "_hoverColor": {
      "__type__": "cc.Color",
      "r": 211,
      "g": 211,
      "b": 211,
      "a": 255
    },
    "_pressedColor": {
      "__type__": "cc.Color",
      "r": 255,
      "g": 255,
      "b": 255,
      "a": 255
    },
    "_disabledColor": {
      "__type__": "cc.Color",
      "r": 124,
      "g": 124,
      "b": 124,
      "a": 255
    },
    "_normalSprite": {
      "__uuid__": "20835ba4-6145-4fbc-a58a-051ce700aa3e@f9941",
      "__expectedType__": "cc.SpriteFrame"
    },
    "_hoverSprite": {
      "__uuid__": "20835ba4-6145-4fbc-a58a-051ce700aa3e@f9941",
      "__expectedType__": "cc.SpriteFrame"
    },
    "_pressedSprite": {
      "__uuid__": "544e49d6-3f05-4fa8-9a9e-091f98fc2ce8@f9941",
      "__expectedType__": "cc.SpriteFrame"
    },
    "_disabledSprite": {
      "__uuid__": "951249e0-9f16-456d-8b85-a6ca954da16b@f9941",
      "__expectedType__": "cc.SpriteFrame"
    },
    "_duration": 0.1,
    "_zoomScale": 1.2,
    "_target": {
      "__id__": 20
    },
    "_id": "8eqwdM2jJF7bMvKArL8axh"
  },
  {
    "__type__": "cc.ClickEvent",
    "target": {
      "__id__": 2
    },
    "component": "",
    "_componentId": "77f44wbrANOP4VV/pktIzil",
    "handler": "isReady",
    "customEventData": ""
  },
  {
    "__type__": "cc.Node",
    "_name": "show ad",
    "_objFlags": 0,
    "_parent": {
      "__id__": 9
    },
    "_children": [
      {
        "__id__": 29
      }
    ],
    "_active": true,
    "_components": [
      {
        "__id__": 32
      },
      {
        "__id__": 33
      },
      {
        "__id__": 34
      }
    ],
    "_prefab": null,
    "_lpos": {
      "__type__": "cc.Vec3",
      "x": 0,
      "y": -100,
      "z": 0
    },
    "_lrot": {
      "__type__": "cc.Quat",
      "x": 0,
      "y": 0,
      "z": 0,
      "w": 1
    },
    "_lscale": {
      "__type__": "cc.Vec3",
      "x": 1,
      "y": 1,
      "z": 1
    },
    "_layer": 33554432,
    "_euler": {
      "__type__": "cc.Vec3",
      "x": 0,
      "y": 0,
      "z": 0
    },
    "_id": "da/t9tSrZOQKUutyfroRVn"
  },
  {
    "__type__": "cc.Node",
    "_name": "SHOW AD",
    "_objFlags": 512,
    "_parent": {
      "__id__": 28
    },
    "_children": [],
    "_active": true,
    "_components": [
      {
        "__id__": 30
      },
      {
        "__id__": 31
      }
    ],
    "_prefab": null,
    "_lpos": {
      "__type__": "cc.Vec3",
      "x": 0,
      "y": 0,
      "z": 0
    },
    "_lrot": {
      "__type__": "cc.Quat",
      "x": 0,
      "y": 0,
      "z": 0,
      "w": 1
    },
    "_lscale": {
      "__type__": "cc.Vec3",
      "x": 1,
      "y": 1,
      "z": 1
    },
    "_layer": 33554432,
    "_euler": {
      "__type__": "cc.Vec3",
      "x": 0,
      "y": 0,
      "z": 0
    },
    "_id": "e1T8dU+QxJZZlSlIr9Ti7U"
  },
  {
    "__type__": "cc.UITransform",
    "_name": "",
    "_objFlags": 0,
    "node": {
      "__id__": 29
    },
    "_enabled": true,
    "__prefab": null,
    "_contentSize": {
      "__type__": "cc.Size",
      "width": 100,
      "height": 40
    },
    "_anchorPoint": {
      "__type__": "cc.Vec2",
      "x": 0.5,
      "y": 0.5
    },
    "_id": "edrTNrdA9PMJDvR2b7tohM"
  },
  {
    "__type__": "cc.Label",
    "_name": "",
    "_objFlags": 0,
    "node": {
      "__id__": 29
    },
    "_enabled": true,
    "__prefab": null,
    "_visFlags": 0,
    "_customMaterial": null,
    "_srcBlendFactor": 2,
    "_dstBlendFactor": 4,
    "_color": {
      "__type__": "cc.Color",
      "r": 0,
      "g": 0,
      "b": 0,
      "a": 255
    },
    "_string": "SHOW AD",
    "_horizontalAlign": 1,
    "_verticalAlign": 1,
    "_actualFontSize": 20,
    "_fontSize": 20,
    "_fontFamily": "Arial",
    "_lineHeight": 40,
    "_overflow": 1,
    "_enableWrapText": false,
    "_font": null,
    "_isSystemFontUsed": true,
    "_spacingX": 0,
    "_isItalic": false,
    "_isBold": false,
    "_isUnderline": false,
    "_underlineHeight": 2,
    "_cacheMode": 0,
    "_id": "edBXUBlIlDnI6y3vL8tHnb"
  },
  {
    "__type__": "cc.UITransform",
    "_name": "",
    "_objFlags": 0,
    "node": {
      "__id__": 28
    },
    "_enabled": true,
    "__prefab": null,
    "_contentSize": {
      "__type__": "cc.Size",
      "width": 200,
      "height": 80
    },
    "_anchorPoint": {
      "__type__": "cc.Vec2",
      "x": 0.5,
      "y": 0.5
    },
    "_id": "8d3dcz9tZOeIPW+wKPEBSe"
  },
  {
    "__type__": "cc.Sprite",
    "_name": "",
    "_objFlags": 0,
    "node": {
      "__id__": 28
    },
    "_enabled": true,
    "__prefab": null,
    "_visFlags": 0,
    "_customMaterial": null,
    "_srcBlendFactor": 2,
    "_dstBlendFactor": 4,
    "_color": {
      "__type__": "cc.Color",
      "r": 255,
      "g": 255,
      "b": 255,
      "a": 255
    },
    "_spriteFrame": {
      "__uuid__": "20835ba4-6145-4fbc-a58a-051ce700aa3e@f9941",
      "__expectedType__": "cc.SpriteFrame"
    },
    "_type": 1,
    "_fillType": 0,
    "_sizeMode": 0,
    "_fillCenter": {
      "__type__": "cc.Vec2",
      "x": 0,
      "y": 0
    },
    "_fillStart": 0,
    "_fillRange": 0,
    "_isTrimmedMode": true,
    "_useGrayscale": false,
    "_atlas": null,
    "_id": "f3z8v1MztPrZA/szc+k2t9"
  },
  {
    "__type__": "cc.Button",
    "_name": "",
    "_objFlags": 0,
    "node": {
      "__id__": 28
    },
    "_enabled": true,
    "__prefab": null,
    "clickEvents": [
      {
        "__id__": 35
      }
    ],
    "_interactable": true,
    "_transition": 2,
    "_normalColor": {
      "__type__": "cc.Color",
      "r": 214,
      "g": 214,
      "b": 214,
      "a": 255
    },
    "_hoverColor": {
      "__type__": "cc.Color",
      "r": 211,
      "g": 211,
      "b": 211,
      "a": 255
    },
    "_pressedColor": {
      "__type__": "cc.Color",
      "r": 255,
      "g": 255,
      "b": 255,
      "a": 255
    },
    "_disabledColor": {
      "__type__": "cc.Color",
      "r": 124,
      "g": 124,
      "b": 124,
      "a": 255
    },
    "_normalSprite": {
      "__uuid__": "20835ba4-6145-4fbc-a58a-051ce700aa3e@f9941",
      "__expectedType__": "cc.SpriteFrame"
    },
    "_hoverSprite": {
      "__uuid__": "20835ba4-6145-4fbc-a58a-051ce700aa3e@f9941",
      "__expectedType__": "cc.SpriteFrame"
    },
    "_pressedSprite": {
      "__uuid__": "544e49d6-3f05-4fa8-9a9e-091f98fc2ce8@f9941",
      "__expectedType__": "cc.SpriteFrame"
    },
    "_disabledSprite": {
      "__uuid__": "951249e0-9f16-456d-8b85-a6ca954da16b@f9941",
      "__expectedType__": "cc.SpriteFrame"
    },
    "_duration": 0.1,
    "_zoomScale": 1.2,
    "_target": {
      "__id__": 28
    },
    "_id": "27h1Jb7aBDL7W0BvXbLKv4"
  },
  {
    "__type__": "cc.ClickEvent",
    "target": {
      "__id__": 2
    },
    "component": "",
    "_componentId": "77f44wbrANOP4VV/pktIzil",
    "handler": "showAd",
    "customEventData": ""
  },
  {
    "__type__": "cc.Node",
    "_name": "back",
    "_objFlags": 0,
    "_parent": {
      "__id__": 9
    },
    "_children": [
      {
        "__id__": 37
      }
    ],
    "_active": true,
    "_components": [
      {
        "__id__": 40
      },
      {
        "__id__": 41
      },
      {
        "__id__": 42
      }
    ],
    "_prefab": null,
    "_lpos": {
      "__type__": "cc.Vec3",
      "x": -200,
      "y": 200,
      "z": 0
    },
    "_lrot": {
      "__type__": "cc.Quat",
      "x": 0,
      "y": 0,
      "z": 0,
      "w": 1
    },
    "_lscale": {
      "__type__": "cc.Vec3",
      "x": 1,
      "y": 1,
      "z": 1
    },
    "_layer": 33554432,
    "_euler": {
      "__type__": "cc.Vec3",
      "x": 0,
      "y": 0,
      "z": 0
    },
    "_id": "383SsCf2JBV6dwk+52H4MY"
  },
  {
    "__type__": "cc.Node",
    "_name": "BACK",
    "_objFlags": 512,
    "_parent": {
      "__id__": 36
    },
    "_children": [],
    "_active": true,
    "_components": [
      {
        "__id__": 38
      },
      {
        "__id__": 39
      }
    ],
    "_prefab": null,
    "_lpos": {
      "__type__": "cc.Vec3",
      "x": 0,
      "y": 0,
      "z": 0
    },
    "_lrot": {
      "__type__": "cc.Quat",
      "x": 0,
      "y": 0,
      "z": 0,
      "w": 1
    },
    "_lscale": {
      "__type__": "cc.Vec3",
      "x": 1,
      "y": 1,
      "z": 1
    },
    "_layer": 33554432,
    "_euler": {
      "__type__": "cc.Vec3",
      "x": 0,
      "y": 0,
      "z": 0
    },
    "_id": "3f/cZmoU1EZpFfbTZhHzCp"
  },
  {
    "__type__": "cc.UITransform",
    "_name": "",
    "_objFlags": 0,
    "node": {
      "__id__": 37
    },
    "_enabled": true,
    "__prefab": null,
    "_contentSize": {
      "__type__": "cc.Size",
      "width": 200,
      "height": 80
    },
    "_anchorPoint": {
      "__type__": "cc.Vec2",
      "x": 0.5,
      "y": 0.5
    },
    "_id": "d3L68MHUxFrqob3vWrk+Kw"
  },
  {
    "__type__": "cc.Label",
    "_name": "",
    "_objFlags": 0,
    "node": {
      "__id__": 37
    },
    "_enabled": true,
    "__prefab": null,
    "_visFlags": 0,
    "_customMaterial": null,
    "_srcBlendFactor": 2,
    "_dstBlendFactor": 4,
    "_color": {
      "__type__": "cc.Color",
      "r": 0,
      "g": 0,
      "b": 0,
      "a": 255
    },
    "_string": "BACK",
    "_horizontalAlign": 1,
    "_verticalAlign": 1,
    "_actualFontSize": 20,
    "_fontSize": 20,
    "_fontFamily": "Arial",
    "_lineHeight": 40,
    "_overflow": 1,
    "_enableWrapText": false,
    "_font": null,
    "_isSystemFontUsed": true,
    "_spacingX": 0,
    "_isItalic": false,
    "_isBold": false,
    "_isUnderline": false,
    "_underlineHeight": 2,
    "_cacheMode": 0,
    "_id": "f7f4ej8jRDxqOjIptksLbV"
  },
  {
    "__type__": "cc.UITransform",
    "_name": "",
    "_objFlags": 0,
    "node": {
      "__id__": 36
    },
    "_enabled": true,
    "__prefab": null,
    "_contentSize": {
      "__type__": "cc.Size",
      "width": 200,
      "height": 80
    },
    "_anchorPoint": {
      "__type__": "cc.Vec2",
      "x": 0.5,
      "y": 0.5
    },
    "_id": "85fYOlJhFJvZINCL16q6O5"
  },
  {
    "__type__": "cc.Sprite",
    "_name": "",
    "_objFlags": 0,
    "node": {
      "__id__": 36
    },
    "_enabled": true,
    "__prefab": null,
    "_visFlags": 0,
    "_customMaterial": null,
    "_srcBlendFactor": 2,
    "_dstBlendFactor": 4,
    "_color": {
      "__type__": "cc.Color",
      "r": 255,
      "g": 255,
      "b": 255,
      "a": 255
    },
    "_spriteFrame": {
      "__uuid__": "20835ba4-6145-4fbc-a58a-051ce700aa3e@f9941",
      "__expectedType__": "cc.SpriteFrame"
    },
    "_type": 1,
    "_fillType": 0,
    "_sizeMode": 0,
    "_fillCenter": {
      "__type__": "cc.Vec2",
      "x": 0,
      "y": 0
    },
    "_fillStart": 0,
    "_fillRange": 0,
    "_isTrimmedMode": true,
    "_useGrayscale": false,
    "_atlas": null,
    "_id": "ee29KHzCBPfY7kKJ49X1my"
  },
  {
    "__type__": "cc.Button",
    "_name": "",
    "_objFlags": 0,
    "node": {
      "__id__": 36
    },
    "_enabled": true,
    "__prefab": null,
    "clickEvents": [
      {
        "__id__": 43
      }
    ],
    "_interactable": true,
    "_transition": 2,
    "_normalColor": {
      "__type__": "cc.Color",
      "r": 214,
      "g": 214,
      "b": 214,
      "a": 255
    },
    "_hoverColor": {
      "__type__": "cc.Color",
      "r": 211,
      "g": 211,
      "b": 211,
      "a": 255
    },
    "_pressedColor": {
      "__type__": "cc.Color",
      "r": 255,
      "g": 255,
      "b": 255,
      "a": 255
    },
    "_disabledColor": {
      "__type__": "cc.Color",
      "r": 124,
      "g": 124,
      "b": 124,
      "a": 255
    },
    "_normalSprite": {
      "__uuid__": "20835ba4-6145-4fbc-a58a-051ce700aa3e@f9941",
      "__expectedType__": "cc.SpriteFrame"
    },
    "_hoverSprite": {
      "__uuid__": "20835ba4-6145-4fbc-a58a-051ce700aa3e@f9941",
      "__expectedType__": "cc.SpriteFrame"
    },
    "_pressedSprite": {
      "__uuid__": "544e49d6-3f05-4fa8-9a9e-091f98fc2ce8@f9941",
      "__expectedType__": "cc.SpriteFrame"
    },
    "_disabledSprite": {
      "__uuid__": "951249e0-9f16-456d-8b85-a6ca954da16b@f9941",
      "__expectedType__": "cc.SpriteFrame"
    },
    "_duration": 0.1,
    "_zoomScale": 1.2,
    "_target": {
      "__id__": 36
    },
    "_id": "7br01aD69G75WqqfIYn9Po"
  },
  {
    "__type__": "cc.ClickEvent",
    "target": {
      "__id__": 2
    },
    "component": "",
    "_componentId": "77f44wbrANOP4VV/pktIzil",
    "handler": "back",
    "customEventData": ""
  },
  {
    "__type__": "cc.UITransform",
    "_name": "",
    "_objFlags": 0,
    "node": {
      "__id__": 9
    },
    "_enabled": true,
    "__prefab": null,
    "_contentSize": {
      "__type__": "cc.Size",
      "width": 960,
      "height": 640
    },
    "_anchorPoint": {
      "__type__": "cc.Vec2",
      "x": 0.5,
      "y": 0.5
    },
    "_id": "batCAKBh5Nv4r/UOxj19mz"
  },
  {
    "__type__": "cc.Canvas",
    "_name": "",
    "_objFlags": 0,
    "node": {
      "__id__": 9
    },
    "_enabled": true,
    "__prefab": null,
    "_cameraComponent": {
      "__id__": 11
    },
    "_alignCanvasWithScreen": true,
    "_id": "37/49CycxMmbBKQUf1t3hS"
  },
  {
    "__type__": "cc.Widget",
    "_name": "",
    "_objFlags": 0,
    "node": {
      "__id__": 9
    },
    "_enabled": true,
    "__prefab": null,
    "_alignFlags": 45,
    "_target": null,
    "_left": 0,
    "_right": 0,
    "_top": 0,
    "_bottom": 0,
    "_horizontalCenter": 0,
    "_verticalCenter": 0,
    "_isAbsLeft": true,
    "_isAbsRight": true,
    "_isAbsTop": true,
    "_isAbsBottom": true,
    "_isAbsHorizontalCenter": true,
    "_isAbsVerticalCenter": true,
    "_originalWidth": 0,
    "_originalHeight": 0,
    "_alignMode": 2,
    "_lockFlags": 0,
    "_id": "6fIn5YpBVHtpUiBMY7uSN4"
  },
  {
    "__type__": "77f44wbrANOP4VV/pktIzil",
    "_name": "",
    "_objFlags": 0,
    "node": {
      "__id__": 9
    },
    "_enabled": true,
    "__prefab": null,
    "_id": "84kYIER/hGOpAuMYx99bm6"
  },
  {
    "__type__": "cc.PrefabInfo",
    "fileId": "a34005c2-5ad2-414b-9f3c-ff3eefaadf24"
  },
  {
    "__type__": "cc.SceneGlobals",
    "ambient": {
      "__id__": 50
    },
    "shadows": {
      "__id__": 51
    },
    "_skybox": {
      "__id__": 52
    },
    "fog": {
      "__id__": 53
    },
    "octree": {
      "__id__": 54
    }
  },
  {
    "__type__": "cc.AmbientInfo",
    "_skyColorHDR": {
      "__type__": "cc.Vec4",
      "x": 0.2,
      "y": 0.4980392156862745,
      "z": 0.8,
      "w": 0.520833125
    },
    "_skyColor": {
      "__type__": "cc.Vec4",
      "x": 0.2,
      "y": 0.4980392156862745,
      "z": 0.8,
      "w": 0.520833125
    },
    "_skyIllumHDR": 20000,
    "_skyIllum": 20000,
    "_groundAlbedoHDR": {
      "__type__": "cc.Vec4",
      "x": 0.2,
      "y": 0.2,
      "z": 0.2,
      "w": 1
    },
    "_groundAlbedo": {
      "__type__": "cc.Vec4",
      "x": 0.2,
      "y": 0.2,
      "z": 0.2,
      "w": 1
    },
    "_skyColorLDR": {
      "__type__": "cc.Vec4",
      "x": 0.2,
      "y": 0.5,
      "z": 0.8,
      "w": 1
    },
    "_skyIllumLDR": 0.5208,
    "_groundAlbedoLDR": {
      "__type__": "cc.Vec4",
      "x": 0.2,
      "y": 0.2,
      "z": 0.2,
      "w": 1
    }
  },
  {
    "__type__": "cc.ShadowsInfo",
    "_type": 0,
    "_enabled": false,
    "_normal": {
      "__type__": "cc.Vec3",
      "x": 0,
      "y": 1,
      "z": 0
    },
    "_distance": 0,
    "_shadowColor": {
      "__type__": "cc.Color",
      "r": 76,
      "g": 76,
      "b": 76,
      "a": 255
    },
    "_firstSetCSM": false,
    "_fixedArea": false,
    "_pcf": 0,
    "_bias": 0.1,
    "_normalBias": 0,
    "_near": 0.1,
    "_far": 10,
    "_shadowDistance": 100,
    "_invisibleOcclusionRange": 200,
    "_orthoSize": 5,
    "_maxReceived": 4,
    "_size": {
      "__type__": "cc.Vec2",
      "x": 512,
      "y": 512
    },
    "_saturation": 1
  },
  {
    "__type__": "cc.SkyboxInfo",
    "_applyDiffuseMap": false,
    "_envmapHDR": null,
    "_envmap": null,
    "_envmapLDR": null,
    "_diffuseMapHDR": null,
    "_diffuseMapLDR": null,
    "_enabled": false,
    "_useIBL": false,
    "_useHDR": true
  },
  {
    "__type__": "cc.FogInfo",
    "_type": 0,
    "_fogColor": {
      "__type__": "cc.Color",
      "r": 225,
      "g": 225,
      "b": 225,
      "a": 255
    },
    "_enabled": false,
    "_fogDensity": 0.3,
    "_fogStart": 0.5,
    "_fogEnd": 300,
    "_fogAtten": 5,
    "_fogTop": 1.5,
    "_fogRange": 1.2,
    "_accurate": false
  },
  {
    "__type__": "cc.OctreeInfo",
    "_enabled": false,
    "_minPos": {
      "__type__": "cc.Vec3",
      "x": -1024,
      "y": -1024,
      "z": -1024
    },
    "_maxPos": {
      "__type__": "cc.Vec3",
      "x": 1024,
      "y": 1024,
      "z": 1024
    },
    "_depth": 8
  }
]